sckernel/__init__.py
sckernel/__main__.py
sckernel/config.py
sckernel/convertNotebookToScd.py
sckernel/install.py
sckernel/kernel.js
sckernel/kernel.py
sckernel/sclangSub.py
sckernel/window.py
sckernel-0.3.2.dist-info/LICENSE
sckernel-0.3.2.dist-info/METADATA
sckernel-0.3.2.dist-info/WHEEL
sckernel-0.3.2.dist-info/top_level.txt
sckernel-0.3.2.dist-info/RECORD
