Metadata-Version: 2.1
Name: sckernel
Version: 0.3.2
Summary: A SuperCollider kernel for Jupyter Notebooks
Home-page: https://github.com/andrewdavis33/sckernel
Author: Andrew Davis
Author-email: andrewdavis33@gmail.com
License: UNKNOWN
Platform: UNKNOWN
Classifier: Programming Language :: Python :: 3
Classifier: License :: OSI Approved :: MIT License
Classifier: Operating System :: OS Independent
Requires-Python: >=3.7
Requires-Dist: jupyter-client
Requires-Dist: IPython
Requires-Dist: ipykernel
